{"identifier": "", "motion_text": "Report introduction of Senate Substitute Amendment 1 by Joint Committee on Finance, Ayes 13, Noes 0", "motion_classification": [], "start_date": "2026-03-11T05:00:00+00:00", "result": "pass", "organization": "~{\"classification\": \"upper\"}", "legislative_session": "2025", "bill": "ff023510-8667-11f1-aab6-466c9731c1f3", "bill_action": null, "bill_identifier": "AB180", "votes": [], "counts": [{"option": "yes", "value": 13}, {"option": "no", "value": 0}], "sources": [{"url": "https://docs.legis.wisconsin.gov/document/journals/2025/hist227795", "note": ""}], "extras": {}, "dedupe_key": "hist227795-AB180", "_id": "ff050d3a-8667-11f1-aab6-466c9731c1f3"}