{"identifier": "", "motion_text": "Assembly Amendment 1 laid on table, Ayes 51, Noes 45", "motion_classification": [], "start_date": "2025-10-14T05:00:00+00:00", "result": "pass", "organization": "~{\"classification\": \"lower\"}", "legislative_session": "2025", "bill": "cf713dc0-1b94-11f1-a7c6-0a26e990a425", "bill_action": null, "bill_identifier": "SB66", "votes": [], "counts": [{"option": "yes", "value": 51}, {"option": "no", "value": 45}], "sources": [{"url": "https://docs.legis.wisconsin.gov/document/amends/2025/REG/SB66-AA1", "note": ""}], "extras": {}, "dedupe_key": "SB66-AA1-SB66", "_id": "cf737ec8-1b94-11f1-a7c6-0a26e990a425"}