{"identifier": "", "motion_text": "Report passage recommended by Committee on Judiciary and Public Safety, Ayes 8, Noes 0", "motion_classification": ["passage"], "start_date": "2025-11-11T06:00:00+00:00", "result": "pass", "organization": "~{\"classification\": \"upper\"}", "legislative_session": "2025", "bill": "a236a2dc-ea11-11f0-9e76-9ac6d7ed61ea", "bill_action": null, "bill_identifier": "SB132", "votes": [], "counts": [{"option": "yes", "value": 8}, {"option": "no", "value": 0}], "sources": [{"url": "https://docs.legis.wisconsin.gov/document/journals/2025/hist213279", "note": ""}], "extras": {}, "dedupe_key": "hist213279-SB132", "_id": "a23781fc-ea11-11f0-9e76-9ac6d7ed61ea"}