{"identifier": "", "motion_text": "Assembly Substitute Amendment 1 laid on table, Ayes 56, Noes 43", "motion_classification": [], "start_date": "2026-01-13T06:00:00+00:00", "result": "pass", "organization": "~{\"classification\": \"lower\"}", "legislative_session": "2025", "bill": "2ba373d2-859f-11f1-885c-ce81da58826b", "bill_action": null, "bill_identifier": "AB182", "votes": [], "counts": [{"option": "yes", "value": 56}, {"option": "no", "value": 43}], "sources": [{"url": "https://docs.legis.wisconsin.gov/document/amends/2025/REG/AB182-ASA1", "note": ""}], "extras": {}, "dedupe_key": "AB182-ASA1-AB182", "_id": "2ba6193e-859f-11f1-885c-ce81da58826b"}