{"identifier": "", "motion_text": "Report passage recommended by Committee on Agriculture and Revenue, Ayes 5, Noes 3", "motion_classification": ["passage"], "start_date": "2026-02-13T06:00:00+00:00", "result": "pass", "organization": "~{\"classification\": \"upper\"}", "legislative_session": "2025", "bill": "dfcf538c-84d5-11f1-86dc-5ac631eadb37", "bill_action": null, "bill_identifier": "SB994", "votes": [], "counts": [{"option": "yes", "value": 5}, {"option": "no", "value": 3}], "sources": [{"url": "https://docs.legis.wisconsin.gov/document/journals/2025/hist224212", "note": ""}], "extras": {}, "dedupe_key": "hist224212-SB994", "_id": "dfd07b18-84d5-11f1-86dc-5ac631eadb37"}