{"identifier": "", "motion_text": "Senate Amendment 2 to Senate Substitute Amendment 2 rejected, Ayes 18, Noes 15", "motion_classification": [], "start_date": "2025-07-02T05:00:00+00:00", "result": "pass", "organization": "~{\"classification\": \"upper\"}", "legislative_session": "2025", "bill": "dd69ec32-f8fe-11f0-a991-2610c6d789b1", "bill_action": null, "bill_identifier": "SB45", "votes": [], "counts": [{"option": "yes", "value": 18}, {"option": "no", "value": 15}], "sources": [{"url": "https://docs.legis.wisconsin.gov/document/amends/2025/REG/SB45-SSA2-SA2", "note": ""}], "extras": {}, "dedupe_key": "SB45-SSA2-SA2-SB45", "_id": "dd6de4ae-f8fe-11f0-a991-2610c6d789b1"}