{"identifier": "", "motion_text": "Report concurrence recommended by Committee on Judiciary and Public Safety, Ayes 5, Noes 3", "motion_classification": ["passage"], "start_date": "2025-05-08T05:00:00+00:00", "result": "pass", "organization": "~{\"classification\": \"upper\"}", "legislative_session": "2025", "bill": "0f9c99f0-0338-11f1-86be-6e5f709afe4e", "bill_action": null, "bill_identifier": "AB73", "votes": [], "counts": [{"option": "yes", "value": 5}, {"option": "no", "value": 3}], "sources": [{"url": "https://docs.legis.wisconsin.gov/document/journals/2025/hist203538", "note": ""}], "extras": {}, "dedupe_key": "hist203538-AB73", "_id": "0f9f7774-0338-11f1-86be-6e5f709afe4e"}