{"identifier": "", "motion_text": "Report passage recommended by Committee on Education, Ayes 12, Noes 0", "motion_classification": ["passage"], "start_date": "2025-11-12T06:00:00+00:00", "result": "pass", "organization": "~{\"classification\": \"lower\"}", "legislative_session": "2025", "bill": "f228b486-5b51-11f1-9b49-266499e987cc", "bill_action": null, "bill_identifier": "AB394", "votes": [], "counts": [{"option": "yes", "value": 12}, {"option": "no", "value": 0}], "sources": [{"url": "https://docs.legis.wisconsin.gov/document/journals/2025/hist213540", "note": ""}], "extras": {}, "dedupe_key": "hist213540-AB394", "_id": "f2297d80-5b51-11f1-9b49-266499e987cc"}